gmql/__init__.py
gmql/FileManagment/DependencyManager.py
gmql/FileManagment/SessionFileManager.py
gmql/FileManagment/TempFileManager.py
gmql/FileManagment/__init__.py
gmql/RemoteConnection/RemoteManager.py
gmql/RemoteConnection/SessionManager.py
gmql/RemoteConnection/__init__.py
gmql/dataset/GDataframe.py
gmql/dataset/GMQLDataset.py
gmql/dataset/__init__.py
gmql/dataset/DataStructures/Aggregates.py
gmql/dataset/DataStructures/ExpressionNodes.py
gmql/dataset/DataStructures/GenometricPredicates.py
gmql/dataset/DataStructures/MetaField.py
gmql/dataset/DataStructures/RegField.py
gmql/dataset/DataStructures/__init__.py
gmql/dataset/loaders/Loader.py
gmql/dataset/loaders/Materializations.py
gmql/dataset/loaders/MemoryLoader.py
gmql/dataset/loaders/MetaLoaderFile.py
gmql/dataset/loaders/MetadataProfiler.py
gmql/dataset/loaders/RegLoaderFile.py
gmql/dataset/loaders/Sources.py
gmql/dataset/loaders/__init__.py
gmql/dataset/parsers/MetadataParser.py
gmql/dataset/parsers/Parsers.py
gmql/dataset/parsers/RegionParser.py
gmql/dataset/parsers/__init__.py
gmql/dataset/storers/FrameToGMQL.py
gmql/dataset/storers/__init__.py
gmql/dataset/storers/parserToXML.py
gmql/ml/algorithms/__init__.py
gmql/ml/algorithms/biclustering.py
gmql/ml/algorithms/classification.py
gmql/ml/algorithms/clustering.py
gmql/ml/algorithms/preprocessing.py
gmql/ml/dataset/__init__.py
gmql/ml/dataset/parser/__init__.py
gmql/ml/dataset/parser/parser.py
gmql/resources/dependencies.xml
gmql/resources/github_url
gmql/resources/version
gmql/resources/hadoop/bin/winutils.exe
gmql-0.0.12.data/scripts/pygmql.sh
gmql-0.0.12.data/scripts/pygmql_login.py
gmql-0.0.12.data/scripts/pygmql_win.bat
gmql-0.0.12.dist-info/DESCRIPTION.rst
gmql-0.0.12.dist-info/METADATA
gmql-0.0.12.dist-info/RECORD
gmql-0.0.12.dist-info/WHEEL
gmql-0.0.12.dist-info/metadata.json
gmql-0.0.12.dist-info/top_level.txt
